thai_id_descriptor/__init__.py
thai_id_descriptor/core.py
thai_id_descriptor-0.1.2.dist-info/LICENSE
thai_id_descriptor-0.1.2.dist-info/METADATA
thai_id_descriptor-0.1.2.dist-info/WHEEL
thai_id_descriptor-0.1.2.dist-info/top_level.txt
thai_id_descriptor-0.1.2.dist-info/RECORD
